AUTHORS.rst
CONTRIBUTING.rst
HISTORY.md
LICENSE
MANIFEST.in
README.md
setup.py
bratabase_social_auth/__init__.py
bratabase_social_auth/backends/__init__.py
bratabase_social_auth/backends/bratabase.py
bratabase_social_auth_backend.egg-info/PKG-INFO
bratabase_social_auth_backend.egg-info/SOURCES.txt
bratabase_social_auth_backend.egg-info/dependency_links.txt
bratabase_social_auth_backend.egg-info/top_level.txt