Metadata-Version: 1.1
Name: bratabase-social-auth-backend
Version: 0.1.2
Summary: OAuth2 Backend for Bratabase.com to be used with Django-social-auth
Home-page: https://github.com/bratabase/bratabase-social-auth-backend
Author: Jj
Author-email: contact@bratabase.com
License: BSD
Keywords: bratabase-social-auth-backend
Platform: UNKNOWN
Classifier: Development Status :: 2 - Pre-Alpha
Classifier: Intended Audience :: Developers
Classifier: License :: OSI Approved :: BSD License
Classifier: Natural Language :: English
Classifier: Programming Language :: Python :: 2
Classifier: Programming Language :: Python :: 2.6
Classifier: Programming Language :: Python :: 2.7
